clover/__init__.py
clover/clusterer/__init__.py
clover/clusterer/_som.py
clover/distribution/__init__.py
clover/distribution/_density.py
clover/distribution/base.py
clover/over_sampling/__init__.py
clover/over_sampling/_cluster.py
clover/over_sampling/_gsomo.py
clover/over_sampling/_kmeans_smote.py
clover/over_sampling/_somo.py
clover/py.typed
cluster_over_sampling-0.6.0.dist-info/WHEEL
cluster_over_sampling-0.6.0.dist-info/METADATA
cluster_over_sampling-0.6.0.dist-info/licenses/LICENSE
cluster_over_sampling-0.6.0.dist-info/RECORD
