Metadata-Version: 2.1
Name: cluster-over-sampling
Version: 0.6.0
Summary: A general interface for clustering based over-sampling algorithms.
License: MIT
Keywords: machine learning,imbalanced learning,oversampling
Author-email: Georgios Douzas <gdouzas@icloud.com>
Requires-Python: >=3.10, <3.12
Classifier: Development Status :: 4 - Beta
Classifier: Intended Audience :: Developers
Classifier: Programming Language :: Python
Classifier: Programming Language :: Python :: 3
Classifier: Programming Language :: Python :: 3 :: Only
Classifier: Programming Language :: Python :: 3.10
Classifier: Programming Language :: Python :: 3.11
Classifier: Topic :: Documentation
Classifier: Topic :: Software Development
Classifier: Topic :: Utilities
Classifier: Typing :: Typed
Requires-Dist: geometric-smote>=0.2.0
Requires-Dist: imbalanced-learn>=0.9.0
Requires-Dist: numpy>=1.22
Requires-Dist: scikit-learn>=1.1.1
Requires-Dist: scipy>=1.7.2
Requires-Dist: typing-extensions>=4.8.0
Provides-Extra: som
Requires-Dist: somoclu>=1.7.6; extra == "som"
Project-URL: Changelog, https://georgedouzas.github.io/cluster-over-sampling/changelog
Project-URL: Discussions, https://github.com/georgedouzas/cluster-over-sampling/discussions
Project-URL: Documentation, https://georgedouzas.github.io/cluster-over-sampling
Project-URL: Funding, https://github.com/sponsors/georgedouzas
Project-URL: Gitter, https://gitter.im/cluster-over-sampling/community
Project-URL: Homepage, https://georgedouzas.github.io/cluster-over-sampling
Project-URL: Issues, https://github.com/georgedouzas/cluster-over-sampling/issues
Project-URL: Repository, https://github.com/georgedouzas/cluster-over-sampling
